{
  "categories": [
    {
      "id": "soguk-kahveler",
      "name": "Soğuk Kahveler",
      "slug": "soguk-kahveler",
      "products": []
    },
    {
      "id": "sicak-icecekler",
      "name": "Sıcak içecekler",
      "slug": "sicak-icecekler",
      "products": [
        {
          "id": "bardak-süt",
          "name": "Bardak Süt",
          "price": 45,
          "price_display": "45₺",
          "description_tr": null,
          "image": null
        },
        {
          "id": "çay-(bardak)",
          "name": "Çay (Bardak)",
          "price": 55,
          "price_display": "55₺",
          "description_tr": null,
          "image": "https://res.cloudinary.com/dcsixrbqw/image/upload/v1775474800/demlemecay_weqqty.jpg"
        },
        {
          "id": "fincan-çay",
          "name": "Fincan Çay",
          "price": 65,
          "price_display": "65₺",
          "description_tr": null,
          "image": null
        }
      ]
    },

    {
      "id": "filtreturk",
      "name": "Filtre & Türk kahvesi",
      "slug": "filtreturk",
      "products": [
        {
          "id": "filtre-kahve",
          "name": "Filtre Kahve",
          "price": 155,
          "price_display": "155₺",
          "description_tr": "Filtre yöntemiyle demlenmiş yumuşak kahve",
          "image": "https://res.cloudinary.com/dcsixrbqw/image/upload/v1775474827/filtrekahve_oo8xay.jpg"
        },
        {
          "id": "türk-kahvesi-",
          "name": "Türk Kahvesi",
          "price": 125,
          "price_display": "125₺",
          "description_tr": "Geleneksel Türk kahvesi",
          "image": "https://res.cloudinary.com/dcsixrbqw/image/upload/v1775475134/tu%CC%88rkkahvesi_vnffln.jpg"
        },
        {
          "id": "double-türk-kahvesi",
          "name": "Double Türk Kahvesi",
          "price": 150,
          "price_display": "150₺",
          "description_tr": "Geleneksel Türk kahvesi",
          "image": "https://res.cloudinary.com/dcsixrbqw/image/upload/v1775475134/tu%CC%88rkkahvesi_vnffln.jpg"
        },
        {
          "id": "bihter-sahlep",
          "name": "Bihter Sahlep",
          "price": 145,
          "price_display": "145₺",
          "description_tr": null,
          "image": "https://res.cloudinary.com/dcsixrbqw/image/upload/v1775475096/salep_x986im.jpg"
        }
      ]
    },

    {
      "id": "espresso-bazli",
      "name": "Espresso bazlı Kahveler",
      "slug": "espresso-bazli",
      "products": [
        {
          "id": "espresso",
          "name": "Espresso",
          "price": 145,
          "price_display": "145₺",
          "description_tr": "Yoğun aromalı tek shot espresso",
          "image": "https://res.cloudinary.com/dcsixrbqw/image/upload/v1775474795/espresssoc_aqoyn2.png"
        },
        {
          "id": "double-espresso",
          "name": "Double Espresso",
          "price": 155,
          "price_display": "155₺",
          "description_tr": "Çift shot yoğun espresso",
          "image": "https://res.cloudinary.com/dcsixrbqw/image/upload/v1775475136/wakeup_ka4e2o.jpg"
        },
        {
          "id": "americano",
          "name": "Americano",
          "price": 165,
          "price_display": "165₺",
          "description_tr": "Espresso ve sıcak su",
          "image": "https://res.cloudinary.com/dcsixrbqw/image/upload/v1775474704/americano_awgwcb.jpg"
        }
      ]
    }
  ]
}
